{
  "title": "Alerta extremo de misantropia em Curitiba: o que aconteceu com o sistema de emergencia?",
  "slug": "alerta-extremo-misantropia-curitiba-defesa-civil",
  "summary": "Na noite de 19 de junho de 2026, milhares de curitibanos receberam um alerta extremo no celular com uma unica palavra: misantropia. A Defesa Civil negou ter enviado. Entenda o que e o Cell Broadcast, quem pode disparar alertas e o que pode ter dado errado.",
  "metaTitle": "Alerta de misantropia em Curitiba: o que aconteceu? | CuritibaBlog",
  "metaDescription": "Curitibanos receberam alerta extremo com a palavra misantropia. Defesa Civil negou autoria. Entenda o Cell Broadcast e o que pode ter causado o disparo.",
  "category": "tecnologia",
  "categories": ["tecnologia"],
  "tags": ["curitiba", "defesa civil", "alerta emergencia", "cell broadcast", "misantropia", "anatel", "alertas celular"],
  "content": "<h2>O que aconteceu na noite de 19 de junho em Curitiba</h2><p>Na noite de sexta-feira, 19 de junho de 2026, milhares de celulares em Curitiba tocaram ao mesmo tempo com um som estridente e uma mensagem marcada como <strong>alerta extremo</strong>. O conteudo do aviso era incomum: apenas a palavra <strong>misantropia</strong>.</p><p>O disparo aconteceu durante o jogo do Brasil contra o Haiti, o que amplificou a confusao. Nas redes sociais, as reacoes foram imediatas: memes, teorias da conspiracao e, claro, a pergunta que todo mundo fez ao mesmo tempo: isso e real?</p><p>A resposta rapida das autoridades foi que nao havia nenhum risco real. Mas a duvida sobre quem enviou o alerta e como isso foi possivel ficou no ar.</p><h2>O que e o Cell Broadcast e como ele funciona</h2><p>O <strong>Cell Broadcast</strong> e o sistema tecnico usado para enviar mensagens de emergencia para todos os celulares dentro de uma area geografica ao mesmo tempo. Diferente de um SMS comum, ele nao precisa do numero de telefone do destinatario. A mensagem e transmitida pelas antenas de telefonia para qualquer aparelho conectado aquela celula de rede.</p><p>O sistema foi criado justamente para situacoes de emergencia massiva: enchentes, terremotos, tsunamis, incendios de grandes proporcoes. A vantagem e a velocidade e o alcance. Quando ha risco real, e um dos mecanismos mais rapidos para avisar a populacao.</p><p>No Brasil, o sistema e gerenciado pela <strong>Anatel</strong> e operado em conjunto com as defesas civis estaduais e municipais. Apenas entidades autorizadas podem disparar alertas. Pelo menos, e assim que deveria funcionar.</p><h2>O que e misantropia e por que a palavra causou estranheza</h2><p><strong>Misantropia</strong> e a aversao, o desprezo ou a desconfianca generalizada pelo ser humano. E um conceito filosofico e psicologico, nao um fenomeno climatico ou emergencia ambiental. Nao tem nada a ver com os motivos pelos quais um alerta de emergencia e disparado.</p><p>Por isso a confusao foi tao grande. Ninguem esperava ver essa palavra numa notificacao de <em>alerta extremo</em>. Algumas pessoas pensaram que era um erro de digitacao. Outras imaginaram que seria um codigo de alguma operacao. Houve quem brincasse com a ideia de que os ETs estavam chegando.</p><p>A realidade e mais prosaica: provavelmente alguem com acesso ao sistema disparou a mensagem por acidente ou como teste, sem perceber que o conteudo iria para os celulares de toda a cidade.</p><h2>O que disse a Defesa Civil e as autoridades</h2><p>A <strong>Defesa Civil do Parana</strong> foi rapida em se pronunciar: o alerta nao saiu deles. A nota oficial descartou qualquer emergencia real e informou que a populacao nao estava em risco.</p><p>A <strong>Prefeitura de Curitiba</strong> tambem confirmou que nao havia situacao de risco que justificasse qualquer aviso naquele momento. As autoridades municipais nao tinham emitido nenhuma ordem de alerta.</p><p>A <strong>Anatel</strong> foi acionada para investigar a origem do disparo. O orgao tem obrigacao de identificar qual entidade autorizou o envio e como a mensagem com aquele conteudo passou pelos filtros do sistema.</p><h2>Como o sistema de alertas pode ser acionado por engano</h2><p>Sistemas de alerta de massa tem camadas de autorizacao, mas nao sao infaliveis. Um operador com credenciais validas pode enviar uma mensagem de teste sem perceber que selecionou o canal de producao em vez do ambiente de homologacao. Isso ja aconteceu em outros paises.</p><p>Em 2018, no Hawaii, um alerta de missil balistico foi enviado para toda a populacao do estado por um operador que clicou na opcao errada durante um exercicio. O panico durou 38 minutos ate a correcao oficial. A situacao em Curitiba foi parecida em natureza, mas sem a gravidade daquele conteudo.</p><p>Outra possibilidade e um sistema de integracao mal configurado que disparou uma mensagem de teste com dados incorretos. Independente da causa tecnica, a Anatel precisa publicar o resultado da investigacao para restaurar a confianca no sistema.</p><h2>Por que alertas de emergencia sao importantes e nao podem perder credibilidade</h2><p>O Cell Broadcast so funciona se a populacao confia nele. Cada alerta falso ou com conteudo incompreensivel corroe essa confianca. Se as pessoas comecam a ignorar os alertas porque 'provavelmente e outro erro', o sistema falha exatamente no momento em que e mais necessario.</p><p>Em paises como o Japao e a Coreia do Sul, sistemas de alerta funcionam ha decadas com alta precisao justamente porque sao testados com rigor e qualquer falha e investigada e publicizada. O Brasil esta expandindo o uso do Cell Broadcast, e episodios como esse precisam ser tratados com seriedade.</p><p>A transparencia da Anatel sobre o resultado da investigacao e fundamental. Nao so para explicar o que aconteceu, mas para mostrar que o sistema tem mecanismos de controle efetivos.</p><h2>O que fazer quando receber um alerta de emergencia no celular</h2><p>A primeira reacao ao receber um alerta extremo deve ser levar a serio ate ter informacoes contrarias. Mesmo que o conteudo pareca estranho, nao descarte de imediato. Verifique rapidamente as fontes oficiais: site da Defesa Civil, perfis oficiais nas redes sociais, grandes portais de noticias locais.</p><p>Se o alerta tiver conteudo claramente sem sentido, como uma palavra filosofica isolada, e razoavel buscar confirmacao antes de tomar qualquer acao. Mas o padrao deve ser sempre verificar primeiro, questionar depois.</p><p>Em situacoes reais de emergencia, os alertas vem acompanhados de instrucoes claras: o que fazer, onde ir, o que evitar. A ausencia de qualquer instrucao pratica e um sinal de que algo esta errado com a mensagem.</p><h2>Casos similares no mundo e o que eles ensinaram</h2><p>O caso do Hawaii em 2018 e o mais famoso, mas nao e o unico. Em 2022, a Finlandia disparou um alerta de teste que chegou aos celulares de cidadaos em horario fora do programado. Em Portugal, um teste do sistema de alertas foi acidentalmente enviado para toda Lisboa em 2021.</p><p>Em todos esses casos, a investigacao rapida e a comunicacao clara das autoridades foram essenciais para conter o panico. O que diferencia os episodios bem gerenciados dos mal gerenciados e justamente a velocidade e a clareza da resposta oficial.</p><p>Curitiba teve uma resposta rapida da Defesa Civil negando o alerta, o que foi positivo. O proximo passo necessario e a explicacao tecnica completa da Anatel sobre o que falhou.</p><h2>O sistema de alertas no Brasil: onde estamos</h2><p>O Brasil adotou o Cell Broadcast de forma mais ampla nos ultimos anos, especialmente apos as tragicas enchentes no Rio Grande do Sul. O sistema chegou a varios estados e tem sido expandido para cobrir mais tipos de emergencia: chuvas, deslizamentos, riscos tecnologicos.</p><p>A tecnologia e boa. O problema e a governanca em torno dela: quem tem acesso, como os acessos sao controlados, como os testes sao feitos e como os incidentes sao investigados e comunicados. Esses processos ainda estao em maturacao no pais.</p><p>O episodio da misantropia em Curitiba e um lembrete de que infraestrutura critica precisa de processos operacionais rigidos, nao so de tecnologia avancada.</p><h2>O que esperar nos proximos dias</h2><p>A Anatel deve publicar um relatorio sobre a origem do disparo. Acompanhe os canais oficiais da agencia e da Defesa Civil do Parana para a conclusao da investigacao. E provavel que o resultado mostre um erro operacional humano, mas os detalhes importam.</p><p>Se voce e profissional de tecnologia ou trabalha com infraestrutura critica, esse episodio e um bom estudo de caso sobre o que acontece quando sistemas com acesso privilegiado nao tem controles operacionais suficientemente rigorosos. A licao nao e nova, mas continua sendo subestimada.</p><p>Por enquanto, o recado e claro: misantropia nao e emergencia. Mas a falha que gerou o alerta pode ser.</p>",
  "faqs": [
    {
      "question": "O que e misantropia e por que apareceu no alerta da Defesa Civil?",
      "answer": "Misantropia e a aversao ou desconfianca generalizada pelo ser humano. A palavra nao tem relacao com emergencias climaticas ou ambientais. O alerta foi provavelmente um erro operacional ou teste incorreto disparado por alguem com acesso ao sistema Cell Broadcast."
    },
    {
      "question": "O alerta era real? Havia algum risco em Curitiba?",
      "answer": "Nao. A Defesa Civil do Parana negou ter enviado o alerta e a Prefeitura de Curitiba confirmou que nao havia nenhuma situacao de risco. A Anatel foi acionada para investigar a origem do disparo."
    },
    {
      "question": "O que e o Cell Broadcast e quem pode enviar alertas por esse sistema?",
      "answer": "Cell Broadcast e o sistema que envia mensagens para todos os celulares em uma area geografica ao mesmo tempo, sem precisar do numero do destinatario. No Brasil, apenas entidades autorizadas pela Anatel podem disparar alertas, como defesas civis estaduais e municipais."
    },
    {
      "question": "Ja aconteceu algo parecido em outros paises?",
      "answer": "Sim. O caso mais famoso foi no Hawaii em 2018, quando um alerta de missil balistico foi enviado para toda a populacao por erro de um operador durante um exercicio. O panico durou 38 minutos. Casos similares ocorreram na Finlandia e em Portugal."
    },
    {
      "question": "O que devo fazer quando receber um alerta de emergencia no celular?",
      "answer": "Leve a serio inicialmente e verifique nas fontes oficiais: site da Defesa Civil, perfis oficiais nas redes sociais e portais de noticias locais. Alertas reais vem com instrucoes claras. A ausencia de qualquer instrucao pratica e sinal de que algo esta errado com a mensagem."
    }
  ],
  "blocks": [
    {
      "type": "info",
      "title": "O alerta de misantropia: fatos",
      "items": [
        {"label": "Data do incidente", "value": "19 de junho de 2026 (sexta-feira a noite)"},
        {"label": "Tipo de alerta", "value": "Alerta extremo via Cell Broadcast"},
        {"label": "Conteudo da mensagem", "value": "Apenas a palavra 'misantropia'"},
        {"label": "Defesa Civil do Parana", "value": "Negou ter enviado o alerta"},
        {"label": "Orgao investigador", "value": "Anatel (acionada apos o incidente)"},
        {"label": "Risco real para a populacao", "value": "Nenhum confirmado pelas autoridades"}
      ]
    },
    {
      "type": "instagram",
      "handle": "@gazetadopovo",
      "posts": ["DZys15PugQ5"]
    },
    {
      "type": "links",
      "title": "Fontes e links oficiais",
      "items": [
        {"label": "Reportagem Gazeta do Povo", "value": "https://www.gazetadopovo.com.br/parana/misantropia-defesa-civil-aciona-anatel-apos-alerta-extremo-em-curitiba/"},
        {"label": "Defesa Civil do Parana", "value": "https://www.defesacivil.pr.gov.br"},
        {"label": "Anatel - Agencia Nacional de Telecomunicacoes", "value": "https://www.anatel.gov.br"},
        {"label": "Sistema de Alertas Emergenciais - Gov.br", "value": "https://www.gov.br/mdr/pt-br/assuntos/protecao-e-defesa-civil/alertas"}
      ]
    },
    {
      "type": "reviews",
      "title": "O que os curitibanos disseram",
      "items": [
        {
          "name": "Rodrigo Machado",
          "avatar": "https://api.dicebear.com/7.x/avataaars/svg?seed=RodrigoMachado",
          "text": "Tava assistindo o jogo quando o celular vibrou com esse alerta. Misantropia? Achei que era brincadeira, mas o som e a vibracao eram do alerta oficial. Foi bem assustador ate entender o que tinha acontecido."
        },
        {
          "name": "Fernanda Oliveira",
          "avatar": "https://api.dicebear.com/7.x/avataaars/svg?seed=FernandaOliveira",
          "text": "Como desenvolvedora, fiquei curiosa sobre como isso aconteceu tecnicamente. Claramente e um erro operacional no sistema Cell Broadcast. O que me preocupa e que isso pode fazer as pessoas ignorarem alertas reais no futuro."
        },
        {
          "name": "Carlos Eduardo Souza",
          "avatar": "https://api.dicebear.com/7.x/avataaars/svg?seed=CarlosEduardoSouza",
          "text": "Minha familia toda me ligou ao mesmo tempo. Todo mundo em panico. A Defesa Civil demorou alguns minutos pra dar o comunicado oficial. Precisamos de um processo mais rapido de desmentido quando isso acontece."
        }
      ]
    }
  ],
  "card1_titulo": "Alerta falso",
  "card1_texto": "Nenhum risco real para Curitiba",
  "card2_titulo": "Cell Broadcast",
  "card2_texto": "Sistema de alertas em massa por antenas",
  "card3_titulo": "Anatel investiga",
  "card3_texto": "Origem do disparo sob investigacao",
  "subtitulo_capa": "Como uma palavra filosofica virou alerta extremo de emergencia"
}
